CHANGES.rst
DESCRIPTION.rst
LICENSE
MANIFEST.in
README.md
setup.py
src/wai.annotations.imgstats.egg-info/PKG-INFO
src/wai.annotations.imgstats.egg-info/SOURCES.txt
src/wai.annotations.imgstats.egg-info/dependency_links.txt
src/wai.annotations.imgstats.egg-info/entry_points.txt
src/wai.annotations.imgstats.egg-info/namespace_packages.txt
src/wai.annotations.imgstats.egg-info/requires.txt
src/wai.annotations.imgstats.egg-info/top_level.txt
src/wai/annotations/imgstats/format/areahistogram/component/_AreaHistogram.py
src/wai/annotations/imgstats/format/areahistogram/component/__init__.py
src/wai/annotations/imgstats/format/areahistogram/specifier/_AreaHistogramISOutputFormatSpecifier.py
src/wai/annotations/imgstats/format/areahistogram/specifier/_AreaHistogramODOutputFormatSpecifier.py
src/wai/annotations/imgstats/format/areahistogram/specifier/_AreaHistogramOutputFormatSpecifier.py
src/wai/annotations/imgstats/format/areahistogram/specifier/__init__.py
src/wai/annotations/imgstats/format/labeldist/component/_LabelDistribution.py
src/wai/annotations/imgstats/format/labeldist/component/__init__.py
src/wai/annotations/imgstats/format/labeldist/specifier/_LabelDistributionICOutputFormatSpecifier.py
src/wai/annotations/imgstats/format/labeldist/specifier/_LabelDistributionISOutputFormatSpecifier.py
src/wai/annotations/imgstats/format/labeldist/specifier/_LabelDistributionODOutputFormatSpecifier.py
src/wai/annotations/imgstats/format/labeldist/specifier/_LabelDistributionOutputFormatSpecifier.py
src/wai/annotations/imgstats/format/labeldist/specifier/__init__.py